README.md
setup.cfg
setup.py
stats_dist/Binomialdistribution.py
stats_dist/Gaussiandistribution.py
stats_dist/Generaldistribution.py
stats_dist/__init__.py
stats_dist.egg-info/PKG-INFO
stats_dist.egg-info/SOURCES.txt
stats_dist.egg-info/dependency_links.txt
stats_dist.egg-info/not-zip-safe
stats_dist.egg-info/top_level.txt